{"user_info_id":{"name":"user_info_id","schema_type":"int","title":"\u9080\u8bf7\u8005","is_search":true,"is_list":true,"type":"text","default":"","notice":"","class":"","err_message":""},"invitee":{"name":"invitee","schema_type":"int","title":"\u88ab\u9080\u8bf7\u8005","is_search":true,"is_list":true,"type":"text","default":"","notice":"","class":"","err_message":""},"created_at":{"name":"created_at","schema_type":"timestamp","title":"\u521b\u5efa\u65f6\u95f4","is_search":true,"is_list":true,"type":"text","default":"","notice":"","class":"","err_message":""},"status":{"name":"status","schema_type":"tinyint","title":"\u662f\u5426\u663e\u793a\u30101:\u672a\u786e\u8ba4\uff1b2\uff1a\u5df2\u786e\u8ba4\u3011","is_search":true,"is_list":true,"type":"text","default":"","notice":"","class":"","err_message":""}}